ldapauthenticator/__init__.py
ldapauthenticator/ldapauthenticator.py
jupyterhub_ldap_authenticator-0.4.1.dist-info/LICENSE.md
jupyterhub_ldap_authenticator-0.4.1.dist-info/METADATA
jupyterhub_ldap_authenticator-0.4.1.dist-info/WHEEL
jupyterhub_ldap_authenticator-0.4.1.dist-info/top_level.txt
jupyterhub_ldap_authenticator-0.4.1.dist-info/RECORD
