Metadata-Version: 2.1
Name: jupyterhub-ldap-authenticator
Version: 0.4.1
Summary: LDAP Authenticator for JupyterHub
Home-page: https://github.com/hansohn/jupyterhub-ldap-authenticator
Author: Ryan Hansohn
Author-email: info@imnorobot.com
License: MIT
Keywords: ldap,authenticator,authentication,jupyterhub,jupyter
Platform: UNKNOWN
Classifier: Intended Audience :: Developers
Classifier: Intended Audience :: System Administrators
Classifier: Intended Audience :: Science/Research
Classifier: License :: OSI Approved :: MIT License
Classifier: Programming Language :: Python
Classifier: Programming Language :: Python :: 3
Requires-Python: ~=3.5
Requires-Dist: jupyterhub (>=0.8.0)
Requires-Dist: ldap3 (>=2.5)
Requires-Dist: tornado (>=4.1)
Requires-Dist: traitlets (>=4.3.2)
